JumpWayMQTT/Application.py
JumpWayMQTT/Device.py
JumpWayMQTT/__init__.py
JumpWayMQTT/CA/__init__.py
JumpWayMQTT/CA/ca.pem
JumpWayMQTT/Classes/Helpers.py
JumpWayMQTT/Classes/__init__.py
JumpWayMQTT-0.1.5.dist-info/METADATA
JumpWayMQTT-0.1.5.dist-info/WHEEL
JumpWayMQTT-0.1.5.dist-info/top_level.txt
JumpWayMQTT-0.1.5.dist-info/RECORD
